[{"type":"misc/objects","description":"Powers of the various objects of the world.","points":1,"talents":[{"type":["misc/objects",1],"source_code":["1.2.0/data/talents/misc/objects.lua",138],"id":"T_WARD","hard_cap":5,"short_name":"WARD","mode":"activated","range":"1.0","image":"ward.png","use_speed":"1 turn","name":"Ward","points":5,"cooldown":"<acronym class=\"talent-variable\" title=\"Values for<br>talent levels 1-5,<br>talent mastery 1.30\">24.1, 20.2, 16.3, 12.4, 10</acronym>","info_text":"<p>Bring a damage-type-specific ward into being. The ward will fully negate as many attacks of its element as it has charges.</p><p>You can activate the following wards: None</p>"},{"type":["misc/objects",1],"source_code":["1.2.0/data/talents/misc/objects.lua",406],"id":"T_SOUL_PURGE","hard_cap":1,"short_name":"SOUL_PURGE","mode":"activated","range":"1.0","image":"stoic.png","use_speed":"1 turn","name":"Soul Purge","points":1,"cooldown":3,"info_text":"<p>Remove any talent Morrigor has absorbed.</p>"},{"short_name":"DIG_OBJECT","image":"dig_object.png","points":1,"type":["misc/objects",1],"source_code":["1.2.0/data/talents/misc/objects.lua",425],"id":"T_DIG_OBJECT","name":"Dig","use_speed":"1 turn","range":"1.0","hard_cap":1,"mode":"activated","info_text":"<p>Dig/cut a tree/&hellip;</p><p>Digging takes 100 turns (based on your currently best digger available).</p>"},{"cost":"20 equilibrium","short_name":"MENTAL_REFRESH","image":"mental_refresh.png","points":5,"type":["misc/objects",1],"id":"T_MENTAL_REFRESH","source_code":["1.2.0/data/talents/misc/objects.lua",506],"name":"Mental Refresh","equilibrium":20,"use_speed":"1 turn","info_text":"<p>Reset up to 3 wild gift, psionic or cursed talents.</p>","mode":"activated","range":"10.0","cooldown":50},{"type":["misc/objects",1],"source_code":["1.2.0/data/talents/misc/objects.lua",603],"points":1,"id":"T_SHIELDSMAIDEN_AURA","short_name":"SHIELDSMAIDEN_AURA","info_text":"<p>Can block up to 1 hit per 10 turns.</p>","image":"shieldsmaiden_aura.png","name":"Shieldsmaiden Aura","mode":"passive","cooldown":10}],"name":"object techniques"}]