[{"name":"corruption / Shadowflame","values":[{"value":{"cost":"12 vim","multi_require":true,"range":"1.0","vim":12,"use_speed":"Instant","points":5,"require":["Level 0, Mag 12","Level 1, Mag 14","Level 2, Mag 16","Level 3, Mag 18","Level 4, Mag 20"],"type":["corruption/shadowflame",1],"is_spell":true,"id":"T_WRAITHFORM","no_silence":true,"cooldown":30,"image":"wraithform.png","name":"Wraithform","info_text":"<p>Turn into a wraith, allowing you to walk through walls (but not preventing suffocation) for <acronym class=\"talent-variable\" title=\"Values for<br>talent levels 1-5,<br>talent mastery 1.30\">5, 6, 8, 9, 10</acronym> turns.</p><p>Also increases your defense and armour by <acronym class=\"talent-variable\" title=\"Values for<br>talent levels 1-5,<br>talent mastery 1.30\">6, 12, 16, 20, 23</acronym> and <acronym class=\"talent-variable\" title=\"Values for<br>talent levels 1-5,<br>talent mastery 1.30\">6, 10, 13, 16, 18,</acronym> respectively.</p><p>If you are still in a wall when the effect ends you will randomly teleport.</p><p></p>","no_energy":true,"short_name":"WRAITHFORM","source_code":["data/talents/corruptions/shadowflame.lua",20],"mode":"activated"},"type":"changed","value2":{"cost":"20 vim","multi_require":true,"range":"1.0","vim":20,"use_speed":"1 turn","points":5,"require":["Level 0, Mag 12","Level 1, Mag 14","Level 2, Mag 16","Level 3, Mag 18","Level 4, Mag 20"],"type":["corruption/shadowflame",1],"is_spell":true,"id":"T_WRAITHFORM","no_silence":true,"cooldown":30,"name":"Wraithform","image":"wraithform.png","mode":"activated","short_name":"WRAITHFORM","source_code":["data/talents/corruptions/shadowflame.lua",20],"info_text":"<p>Turn into a wraith, allowing you to walk through walls (but not preventing suffocation) for <acronym class=\"talent-variable\" title=\"Values for<br>talent levels 1-5,<br>talent mastery 1.30\">5, 6, 8, 9, 10</acronym> turns.</p><p>Also increases your Defense and Armour by <acronym class=\"variable\" title=\"Values for<br>talent levels 1-5,<br>talent mastery 1.30,<br>spellpower 100\">11, 15, 19, 21, 24</acronym> and <acronym class=\"variable\" title=\"Values for<br>talent levels 1-5,<br>talent mastery 1.30,<br>spellpower 100\">9, 12, 14, 17, 18,</acronym> respectively.</p><p>If you are still in a wall when the effect ends you will randomly teleport.</p><p>The bonuses will increase with your Spellpower.</p>"}}]}]